__init__.py
strava2gpx.py
strava2gpx-1.0.1.dist-info/LICENSE
strava2gpx-1.0.1.dist-info/METADATA
strava2gpx-1.0.1.dist-info/WHEEL
strava2gpx-1.0.1.dist-info/top_level.txt
strava2gpx-1.0.1.dist-info/RECORD
